run_models/__init__.py
run_models-0.0.4.dist-info/LICENSE.txt
run_models-0.0.4.dist-info/METADATA
run_models-0.0.4.dist-info/WHEEL
run_models-0.0.4.dist-info/top_level.txt
run_models-0.0.4.dist-info/RECORD
