Metadata-Version: 2.1
Name: run-models
Version: 0.0.4
Summary: Run all regression and classification models with its default parameters
Home-page: https://github.com/Shivanandroy/run_models/
Author: Shivanand Roy
Author-email: Shivanandroy.official@gmail.com
License: UNKNOWN
Platform: UNKNOWN
Classifier: Programming Language :: Python :: 3
Classifier: License :: OSI Approved :: MIT License
Classifier: Operating System :: OS Independent
Requires-Dist: scikit-learn
Requires-Dist: xgboost
Requires-Dist: lightgbm
Requires-Dist: catboost
Requires-Dist: pandas
Requires-Dist: matplotlib
Requires-Dist: numpy
